{
  "part_of_speech" : "substantif",
  "synonyms" : [ {
    "canonical_form" : "vigueur",
    "other_forms" : [ "vigueurs" ]
  }, {
    "canonical_form" : "force",
    "other_forms" : [ "forces" ]
  }, {
    "canonical_form" : "ardeur",
    "other_forms" : [ "ardeurs" ]
  }, {
    "canonical_form" : "énergie",
    "other_forms" : [ "énergies" ]
  }, {
    "canonical_form" : "vie",
    "other_forms" : [ "vies" ]
  }, {
    "canonical_form" : "vivacité",
    "other_forms" : [ "vivacités" ]
  }, {
    "canonical_form" : "vitalité",
    "other_forms" : [ "vitalités" ]
  }, {
    "canonical_form" : "chaleur",
    "other_forms" : [ "chaleurs" ]
  }, {
    "canonical_form" : "dynamisme",
    "other_forms" : [ "dynamismes" ]
  }, {
    "canonical_form" : "fermeté",
    "other_forms" : [ "fermetés" ]
  }, {
    "canonical_form" : "puissance",
    "other_forms" : [ "puissances" ]
  }, {
    "canonical_form" : "violence",
    "other_forms" : [ "violences" ]
  }, {
    "canonical_form" : "sève",
    "other_forms" : [ "sèves" ]
  }, {
    "canonical_form" : "bouillonnement",
    "other_forms" : [ "bouillonnements" ]
  }, {
    "canonical_form" : "activité",
    "other_forms" : [ "activités" ]
  }, {
    "canonical_form" : "solidité",
    "other_forms" : [ "solidités" ]
  }, {
    "canonical_form" : "véhémence",
    "other_forms" : [ "véhémences" ]
  }, {
    "canonical_form" : "âme",
    "other_forms" : [ "âmes" ]
  }, {
    "canonical_form" : "verdeur",
    "other_forms" : [ "verdeurs" ]
  }, {
    "canonical_form" : "profondeur",
    "other_forms" : [ "profondeurs" ]
  }, {
    "canonical_form" : "virilité",
    "other_forms" : [ "virilités" ]
  }, {
    "canonical_form" : "robustesse",
    "other_forms" : [ "robustesses" ]
  }, {
    "canonical_form" : "nerf",
    "other_forms" : [ "nerfs" ]
  }, {
    "canonical_form" : "hardiesse",
    "other_forms" : [ "hardiesses" ]
  }, {
    "canonical_form" : "générosité",
    "other_forms" : [ "générosités" ]
  }, {
    "canonical_form" : "muscle",
    "other_forms" : [ "muscles" ]
  }, {
    "canonical_form" : "jeunesse",
    "other_forms" : [ "jeunesses" ]
  }, {
    "canonical_form" : "exubérance",
    "other_forms" : [ "exubérances" ]
  }, {
    "canonical_form" : "couleur",
    "other_forms" : [ "couleurs" ]
  }, {
    "canonical_form" : "biceps",
    "other_forms" : [ ]
  }, {
    "canonical_form" : "autorité",
    "other_forms" : [ "autorités" ]
  }, {
    "canonical_form" : "allégresse",
    "other_forms" : [ "allégresses" ]
  }, {
    "canonical_form" : "punch",
    "other_forms" : [ "punchs" ]
  }, {
    "canonical_form" : "pesanteur",
    "other_forms" : [ "pesanteurs" ]
  }, {
    "canonical_form" : "nervosité",
    "other_forms" : [ "nervosités" ]
  }, {
    "canonical_form" : "luxuriance",
    "other_forms" : [ "luxuriances" ]
  }, {
    "canonical_form" : "fringance",
    "other_forms" : [ "fringances" ]
  }, {
    "canonical_form" : "franchise",
    "other_forms" : [ "franchises" ]
  }, {
    "canonical_form" : "application",
    "other_forms" : [ "applications" ]
  }, {
    "canonical_form" : "animosité",
    "other_forms" : [ "animosités" ]
  }, {
    "canonical_form" : "éloquence",
    "other_forms" : [ "éloquences" ]
  } ]
}