{
  "part_of_speech" : "substantif",
  "synonyms" : [ {
    "canonical_form" : "ère",
    "other_forms" : [ "ères" ]
  }, {
    "canonical_form" : "période",
    "other_forms" : [ "périodes" ]
  }, {
    "canonical_form" : "siècle",
    "other_forms" : [ "siècles" ]
  }, {
    "canonical_form" : "époque",
    "other_forms" : [ "époques" ]
  }, {
    "canonical_form" : "temps",
    "other_forms" : [ ]
  }, {
    "canonical_form" : "âge",
    "other_forms" : [ "âges" ]
  }, {
    "canonical_form" : "cycle",
    "other_forms" : [ "cycles" ]
  }, {
    "canonical_form" : "hégire",
    "other_forms" : [ "hégires" ]
  } ]
}